opentaskpy/exceptions.py
opentaskpy/otflogging.py
opentaskpy/taskrun.py
opentaskpy/cli/task_run.py
opentaskpy/config/__init__.py
opentaskpy/config/loader.py
opentaskpy/config/schemas.py
opentaskpy/config/schemas/batch/tasks.json
opentaskpy/config/schemas/execution/local/local.json
opentaskpy/config/schemas/execution/local/protocol.json
opentaskpy/config/schemas/execution/ssh/protocol.json
opentaskpy/config/schemas/execution/ssh/ssh.json
opentaskpy/config/schemas/transfer/email_destination.json
opentaskpy/config/schemas/transfer/local_destination.json
opentaskpy/config/schemas/transfer/local_source.json
opentaskpy/config/schemas/transfer/sftp_destination.json
opentaskpy/config/schemas/transfer/sftp_source.json
opentaskpy/config/schemas/transfer/ssh_destination.json
opentaskpy/config/schemas/transfer/ssh_source.json
opentaskpy/config/schemas/transfer/email/protocol.json
opentaskpy/config/schemas/transfer/local_destination/flags.json
opentaskpy/config/schemas/transfer/local_destination/permissions.json
opentaskpy/config/schemas/transfer/local_destination/protocol.json
opentaskpy/config/schemas/transfer/local_destination/rename.json
opentaskpy/config/schemas/transfer/local_source/conditionals.json
opentaskpy/config/schemas/transfer/local_source/fileWatch.json
opentaskpy/config/schemas/transfer/local_source/postCopyAction.json
opentaskpy/config/schemas/transfer/local_source/protocol.json
opentaskpy/config/schemas/transfer/sftp_destination/flags.json
opentaskpy/config/schemas/transfer/sftp_destination/permissions.json
opentaskpy/config/schemas/transfer/sftp_destination/protocol.json
opentaskpy/config/schemas/transfer/sftp_destination/rename.json
opentaskpy/config/schemas/transfer/sftp_source/conditionals.json
opentaskpy/config/schemas/transfer/sftp_source/fileWatch.json
opentaskpy/config/schemas/transfer/sftp_source/postCopyAction.json
opentaskpy/config/schemas/transfer/sftp_source/protocol.json
opentaskpy/config/schemas/transfer/ssh_destination/flags.json
opentaskpy-0.15.1.dist-info/AUTHORS
opentaskpy-0.15.1.dist-info/LICENSE
opentaskpy-0.15.1.dist-info/METADATA
opentaskpy-0.15.1.dist-info/WHEEL
opentaskpy-0.15.1.dist-info/entry_points.txt
opentaskpy-0.15.1.dist-info/top_level.txt
opentaskpy-0.15.1.dist-info/RECORD
