Metadata-Version: 2.1
Name: opentaskpy
Version: 0.15.1
Summary: A framework for automation execution of commands and transferring files between hosts
Author-email: Adam McDonagh <adam@elitemonkey.net>
License: GPLv3
Project-URL: Homepage, https://github.com/adammcdonagh/open-task-framework
Project-URL: Bug Tracker, https://github.com/adammcdonagh/open-task-framework/issues
Project-URL: Changelog, https://github.com/adammcdonagh/open-task-framework/blob/main/CHANGELOG.md
Keywords: automation,task,framework,scheduling,ssh,sftp,remote,execution,command
Classifier: Programming Language :: Python :: 3
Classifier: License :: OSI Approved :: GNU General Public License v3 (GPLv3)
Classifier: Operating System :: POSIX
Requires-Python: >=3.11
License-File: LICENSE
License-File: AUTHORS
Requires-Dist: jinja2 >=3.1
Requires-Dist: jsonpath-ng >=1.5
Requires-Dist: jsonschema >=4.17
Requires-Dist: paramiko >=3.0
Requires-Dist: requests >=2.28
Requires-Dist: referencing >=0.29.1
Provides-Extra: dev
Requires-Dist: types-requests >=2.28 ; extra == 'dev'
Requires-Dist: types-paramiko >=3.0 ; extra == 'dev'
Requires-Dist: black >=23.1.0 ; extra == 'dev'
Requires-Dist: isort ; extra == 'dev'
Requires-Dist: pytest ; extra == 'dev'
Requires-Dist: bumpver ; extra == 'dev'
Requires-Dist: pytest-shell ; extra == 'dev'
Requires-Dist: lovely-pytest-docker ; extra == 'dev'
Requires-Dist: pre-commit ; extra == 'dev'
Requires-Dist: pylint >=2.17.0 ; extra == 'dev'
Requires-Dist: pydantic ; extra == 'dev'
Requires-Dist: mypy ; extra == 'dev'
Requires-Dist: ruff ; extra == 'dev'
Requires-Dist: coverage ; extra == 'dev'
Requires-Dist: pytest-cov ; extra == 'dev'
